{
  "dao_state": {
    "authority": "HFLJshw3X4eVdBp8GninWzMvYr3frvPwx2566LsKndeS",
    "governance_token_mint": "8uiF41moW2dUwv1WiMT58AmoLcYQU5ZFL4MYHQpg66uy",
    "member_count": 5,
    "proposal_count": 3,
    "treasury_balance": 1000000,
    "message_fee": 1000,
    "relay_reward_rate": 500
  },
  "members": [
    {
      "wallet": "9viEzvBxydW4vXwih9JHqrkKaL8ycSGPvaGsY7q1mKmR",
      "nickname": "Alice_Crypto",
      "voting_power": 1000,
      "joined_at": 1758358363218
    },
    {
      "wallet": "9UumTUPSE9vnwu83eKpBDxGqDt3868myC2F7d2UZdqzF",
      "nickname": "Bob_Builder",
      "voting_power": 800,
      "joined_at": 1759222363218
    },
    {
      "wallet": "2wXJT9MvJmgXS7HURPLfEhMMPsMjWgAe1CSwvhf2jeAN",
      "nickname": "Carol_Validator",
      "voting_power": 1200,
      "joined_at": 1759654363219
    },
    {
      "wallet": "33nSgB1wyGuU9mNSBHcsmTyxJR1uKTUopJz56hXhPHhS",
      "nickname": "Dave_Relay",
      "voting_power": 600,
      "joined_at": 1760086363219
    },
    {
      "wallet": "9eHohdHB32nUcw24RLVoM4ums2AsiHbmbUcXzy366Ttm",
      "nickname": "Eve_Governance",
      "voting_power": 900,
      "joined_at": 1760518363219
    }
  ],
  "proposals": [
    {
      "id": 1,
      "title": "Increase Message Fee to 0.001 SOL",
      "description": "Proposal to increase the message fee from 0.0005 SOL to 0.001 SOL to better compensate relay operators",
      "proposer": "Alice_Crypto",
      "votes_for": 2800,
      "votes_against": 1700,
      "status": "PASSED",
      "created_at": 1760345563219
    },
    {
      "id": 2,
      "title": "Add New Relay Node in Singapore",
      "description": "Proposal to add a new relay node in Singapore to improve message delivery in APAC region",
      "proposer": "Dave_Relay",
      "votes_for": 3200,
      "votes_against": 1300,
      "status": "PASSED",
      "created_at": 1760691163219
    },
    {
      "id": 3,
      "title": "Treasury Allocation for Development",
      "description": "Allocate 10 SOL from treasury for continued development and maintenance",
      "proposer": "Bob_Builder",
      "votes_for": 1800,
      "votes_against": 2700,
      "status": "ACTIVE",
      "created_at": 1760863963219
    }
  ],
  "relay_nodes": [
    {
      "node_id": "5fom1kEgWSkjzBjj32jhCXoxV2EwxASBsh6xCJqZvNaW",
      "operator": "Dave_Relay",
      "location": "New York",
      "uptime": 99.5,
      "messages_processed": 15420,
      "stake_amount": 5000000
    },
    {
      "node_id": "BoTJsTCRyThv3shjM8X9SJHLsb12VuuzrK3X8FZsnbL5",
      "operator": "Carol_Validator",
      "location": "London",
      "uptime": 98.2,
      "messages_processed": 12800,
      "stake_amount": 4000000
    },
    {
      "node_id": "4EbbHEZWR2f3aatWq8uPzmEzPgm94W56ojJgHvyvSoNE",
      "operator": "Alice_Crypto",
      "location": "Singapore",
      "uptime": 99.8,
      "messages_processed": 18600,
      "stake_amount": 6000000
    }
  ]
}